README.md
setup.py
qic/__init__.py
qic/__main__.py
qic/commandline.py
qic/dsq.py
qic/json2html.py
qic/json2table.py
qic/tblfmt.py
qic.egg-info/PKG-INFO
qic.egg-info/SOURCES.txt
qic.egg-info/dependency_links.txt
qic.egg-info/entry_points.txt
qic.egg-info/requires.txt
qic.egg-info/top_level.txt