Metadata-Version: 2.1
Name: qic
Version: 1.1.3
Summary: data(JSON/XML/YAML) command line query tools with interactive mode.
Home-page: https://github.com/walkerever/qic
Author: Yonghang Wang
Author-email: wyhang@gmail.com
License: Apache 2
Keywords: json,yaml,xml,query,jq,dq,dsq,dsquery,qic,dataquery,json query,xml query,yaml query,jello,jq
Platform: UNKNOWN
Classifier: License :: OSI Approved :: Apache Software License
